aircheck/__init__.py
aircheck/integrity_check.py
aircheck/main.py
aircheck/py.typed
aircheck/core/__init__.py
aircheck/core/checks.py
aircheck/core/load.py
aircheck/core/utils.py
aircheck-0.1.2.dist-info/METADATA
aircheck-0.1.2.dist-info/WHEEL
aircheck-0.1.2.dist-info/entry_points.txt
aircheck-0.1.2.dist-info/licenses/LICENSE
aircheck-0.1.2.dist-info/RECORD
